azure/mgmt/videoanalyzer/__init__.py
azure/mgmt/videoanalyzer/_configuration.py
azure/mgmt/videoanalyzer/_version.py
azure/mgmt/videoanalyzer/_video_analyzer.py
azure/mgmt/videoanalyzer/aio/__init__.py
azure/mgmt/videoanalyzer/aio/_configuration.py
azure/mgmt/videoanalyzer/aio/_video_analyzer.py
azure/mgmt/videoanalyzer/aio/operations/__init__.py
azure/mgmt/videoanalyzer/aio/operations/_access_policies_operations.py
azure/mgmt/videoanalyzer/aio/operations/_edge_modules_operations.py
azure/mgmt/videoanalyzer/aio/operations/_live_pipeline_operation_statuses_operations.py
azure/mgmt/videoanalyzer/aio/operations/_live_pipelines_operations.py
azure/mgmt/videoanalyzer/aio/operations/_locations_operations.py
azure/mgmt/videoanalyzer/aio/operations/_operation_results_operations.py
azure/mgmt/videoanalyzer/aio/operations/_operation_statuses_operations.py
azure/mgmt/videoanalyzer/aio/operations/_operations.py
azure/mgmt/videoanalyzer/aio/operations/_pipeline_job_operation_statuses_operations.py
azure/mgmt/videoanalyzer/aio/operations/_pipeline_jobs_operations.py
azure/mgmt/videoanalyzer/aio/operations/_pipeline_topologies_operations.py
azure/mgmt/videoanalyzer/aio/operations/_private_endpoint_connections_operations.py
azure/mgmt/videoanalyzer/aio/operations/_private_link_resources_operations.py
azure/mgmt/videoanalyzer/aio/operations/_video_analyzer_operation_results_operations.py
azure/mgmt/videoanalyzer/aio/operations/_video_analyzer_operation_statuses_operations.py
azure/mgmt/videoanalyzer/aio/operations/_video_analyzers_operations.py
azure/mgmt/videoanalyzer/aio/operations/_videos_operations.py
azure/mgmt/videoanalyzer/models/__init__.py
azure/mgmt/videoanalyzer/models/_models.py
azure/mgmt/videoanalyzer/models/_models_py3.py
azure/mgmt/videoanalyzer/models/_video_analyzer_enums.py
azure/mgmt/videoanalyzer/operations/__init__.py
azure/mgmt/videoanalyzer/operations/_access_policies_operations.py
azure/mgmt/videoanalyzer/operations/_edge_modules_operations.py
azure_mgmt_videoanalyzer-1.0.0b4.dist-info/LICENSE
azure_mgmt_videoanalyzer-1.0.0b4.dist-info/METADATA
azure_mgmt_videoanalyzer-1.0.0b4.dist-info/WHEEL
azure_mgmt_videoanalyzer-1.0.0b4.dist-info/top_level.txt
azure_mgmt_videoanalyzer-1.0.0b4.dist-info/RECORD
